pd3f/__init__.py
pd3f/dehyphen_wrapper.py
pd3f/doc_info.py
pd3f/doc_output.py
pd3f/export.py
pd3f/geometry.py
pd3f/parsr_wrapper.py
pd3f/pd3fConfig.json
pd3f/string_utils.py
pd3f/utils.py
pd3f-0.4.0.dist-info/LICENSE
pd3f-0.4.0.dist-info/WHEEL
pd3f-0.4.0.dist-info/METADATA
pd3f-0.4.0.dist-info/RECORD
