Metadata-Version: 2.1
Name: pd3f
Version: 0.4.0
Summary: Reconstruct the original continuous text from PDFs with language models
Home-page: https://github.com/pd3f/pd3f-core
License: AGPL-3.0-only
Keywords: pdf,nlp,german,text-extraction
Author: Johannes Filter
Author-email: hi@jfilter.de
Requires-Python: >=3.8,<4.0
Classifier: License :: OSI Approved :: GNU Affero General Public License v3
Classifier: Programming Language :: Python :: 3
Classifier: Programming Language :: Python :: 3.8
Classifier: Programming Language :: Python :: 3.9
Classifier: Topic :: Scientific/Engineering :: Artificial Intelligence
Classifier: Topic :: Scientific/Engineering :: Information Analysis
Requires-Dist: clean-text[gpl]
Requires-Dist: dehyphen (>=0.3.0,<0.4.0)
Requires-Dist: joblib
Requires-Dist: parsr-client (==3.1)
Requires-Dist: shapely
Requires-Dist: textdistance
Project-URL: Repository, https://github.com/pd3f/pd3f-core
